README.txt
setup.py
Products/__init__.py
Products.eCards.egg-info/PKG-INFO
Products.eCards.egg-info/SOURCES.txt
Products.eCards.egg-info/dependency_links.txt
Products.eCards.egg-info/entry_points.txt
Products.eCards.egg-info/namespace_packages.txt
Products.eCards.egg-info/not-zip-safe
Products.eCards.egg-info/requires.txt
Products.eCards.egg-info/top_level.txt
Products/eCards/CHANGES.txt
Products/eCards/CREDITS.txt
Products/eCards/INSTALL.txt
Products/eCards/LICENSE.txt
Products/eCards/README.txt
Products/eCards/TODO.txt
Products/eCards/__init__.py
Products/eCards/browser.py
Products/eCards/config.py
Products/eCards/configure.zcml
Products/eCards/interfaces.py
Products/eCards/version.txt
Products/eCards/Extensions/Install.py
Products/eCards/Extensions/__init__.py
Products/eCards/content/__init__.py
Products/eCards/content/ecard.py
Products/eCards/content/ecardcollection.py
Products/eCards/profiles/default/cssregistry.xml
Products/eCards/profiles/default/factorytool.xml
Products/eCards/profiles/default/propertiestool.xml
Products/eCards/profiles/default/rolemap.xml
Products/eCards/profiles/default/skins.xml
Products/eCards/profiles/default/types.xml
Products/eCards/profiles/default/workflows.xml
Products/eCards/profiles/default/types/eCard.xml
Products/eCards/profiles/default/types/eCardCollection.xml
Products/eCards/skins/ecards_images/ecard_icon.gif
Products/eCards/skins/ecards_images/ecardcollection_icon.gif
Products/eCards/skins/ecards_styles/ecards.css.dtml
Products/eCards/skins/ecards_styles/ecards.css.dtml.metadata
Products/eCards/skins/ecards_templates/ecard_form_macro.pt
Products/eCards/skins/ecards_templates/ecardcollection_view.pt
Products/eCards/skins/ecards_templates/ecardpopup_thanks.pt
Products/eCards/skins/ecards_templates/ecardpopup_view.cpt
Products/eCards/skins/ecards_templates/ecardpopup_view.cpt.metadata
Products/eCards/skins/ecards_templates/ecardvalidation.vpy
Products/eCards/skins/ecards_templates/email_template.pt
Products/eCards/skins/ecards_templates/send_ecard.cpy
Products/eCards/skins/ecards_templates/send_ecard.cpy.metadata
Products/eCards/tests/__init__.py
Products/eCards/tests/base.py
Products/eCards/tests/test_browserviews.py
Products/eCards/tests/test_content.py
Products/eCards/tests/test_installation.py
Products/eCards/tests/test_interfaces.py
