Metadata-Version: 1.0
Name: Products.eCards
Version: 1.1rc1
Summary: eCards is a simple product that allows your website visitors to send e-cards to people via email.
Home-page: http://www.plone.org/products/ecards
Author: Andrew Burkhalter
Author-email: andrewburkhalter@gmail.com
License: GPL
Keywords: Plone Archetypes Content
Platform: UNKNOWN
Classifier: Programming Language :: Python
Classifier: Topic :: Software Development :: Libraries :: Python Modules
Classifier: Framework :: Zope2
Classifier: Framework :: Plone
